{"RC":1,"Version":"00000000","SN":1701252870,"PL":{"20170623104823000":{"result":{"country":"中国","city":"北京市","adcode":"110108","poi":"北京市知春里中学-北京市银帆合唱团","type":"3","province":"北京市","citycode":"010","road":"科学院南路","street":"知春路","location":"116.3254647,39.9735463","radius":"25","desc":"北京市 海淀区 科学院南路 靠近北京市知春里中学-北京市银帆合唱团","timestamp":"20170623104823000"},"EID":"8F28166A5064D2763C4FA4AF7F0A41EF","in_zone":"EFID1","SOS":0,"infocode":"10000","dis_EFID1":134.0,"steps":67,"loctype":2,"status":"1","info":"OK","timestamp":"20170623104823000"},"20170623130243000":{"result":{"country":"中国","province":"北京市","citycode":"010","adcode":"110108","city":"北京市","district":"海淀区","location":"116.309298502605,39.978928222657","type":"1","radius":"47","township":"海淀街道","desc":"北京市海淀区海淀街道丹棱街11号1+1大厦(彩和坊路)","timestamp":"20170623130243000"},"EID":"8F28166A5064D2763C4FA4AF7F0A41EF","gps_data":{"altitude":"187.600000","ground_speed":"1.166760","trace_degree":"73.570000"},"SOS":0,"infocode":"10000","dis_EFID1":1379.0,"steps":40,"loctype":2,"status":"1","info":"OK","timestamp":"20170623130243000"},"20170623000251000":{"result":{"country":"中国","province":"北京市","citycode":"010","adcode":"110108","city":"北京市","district":"海淀区","location":"116.309417046441,39.981200629341","type":"1","radius":"48","township":"海淀街道","desc":"北京市海淀区海淀街道海淀西街天创科技大厦","timestamp":"20170623000251000"},"EID":"8F28166A5064D2763C4FA4AF7F0A41EF","gps_data":{"altitude":"108.400000","ground_speed":"6.722760","trace_degree":"197.679993"},"SOS":0,"infocode":"10000","dis_EFID1":1497.0,"steps":17,"loctype":2,"status":"1","info":"OK","timestamp":"20170623000251000"},"20170623194817000":{"result":{"country":"中国","province":"北京市","citycode":"010","adcode":"110108","city":"北京市","district":"海淀区","location":"116.310155164931,39.980077582466","type":"1","radius":"58","township":"海淀街道","desc":"北京市海淀区海淀街道善缘街微软亚太研发集团大厦(微软总部)","timestamp":"20170623194817000"},"EID":"8F28166A5064D2763C4FA4AF7F0A41EF","gps_data":{"altitude":"159.800000","ground_speed":"0.796360","trace_degree":"60.560001"},"SOS":0,"infocode":"10000","dis_EFID1":1376.0,"steps":64,"loctype":2,"status":"1","info":"OK","timestamp":"20170623194817000"},"20170623133641000":{"result":{"country":"中国","province":"北京市","citycode":"010","adcode":"110108","city":"北京市","district":"海淀区","location":"116.30627061632,39.978033040365","type":"1","radius":"55","township":"海淀街道","desc":"北京市海淀区海淀街道苏州街长远天地大厦","timestamp":"20170623133641000"},"EID":"8F28166A5064D2763C4FA4AF7F0A41EF","gps_data":{"altitude":"96.900000","ground_speed":"7.148720","trace_degree":"319.829987"},"SOS":0,"infocode":"10000","dis_EFID1":1582.0,"steps":11,"loctype":2,"status":"1","info":"OK","timestamp":"20170623133641000"},"20170623134101000":{"result":{"country":"中国","city":"北京市","adcode":"110108","poi":"中国邮政储蓄银行(中关村西区支行)","type":"3","province":"北京市","citycode":"010","road":"海淀西街","street":"丹棱街","location":"116.309684,39.9802734","radius":"45","desc":"北京市 海淀区 海淀西街 靠近中国邮政储蓄银行(中关村西区支行)","timestamp":"20170623134101000"},"EID":"8F28166A5064D2763C4FA4AF7F0A41EF","SOS":0,"infocode":"10000","dis_EFID1":1422.0,"steps":103,"loctype":2,"status":"1","info":"OK","timestamp":"20170623134101000"},"20170623105425000":{"result":{"country":"中国","province":"北京市","citycode":"010","adcode":"110108","city":"北京市","district":"海淀区","location":"116.320584581164,39.976343044705","type":"1","radius":"31","township":"中关村街道","desc":"北京市海淀区中关村街道中关村大街110号银网中心","timestamp":"20170623105425000"},"EID":"8F28166A5064D2763C4FA4AF7F0A41EF","gps_data":{"altitude":"70.200000","ground_speed":"9.945240","trace_degree":"243.059998"},"SOS":0,"infocode":"10000","dis_EFID1":416.0,"steps":5,"loctype":2,"status":"1","info":"OK","timestamp":"20170623105425000"},"20170623104942000":{"result":{"country":"中国","city":"北京市","adcode":"110108","poi":"北京市知春里中学-北京市银帆合唱团","type":"3","province":"北京市","citycode":"010","road":"科学院南路","street":"知春路","location":"116.32551,39.9735259","radius":"25","desc":"北京市 海淀区 科学院南路 靠近北京市知春里中学-北京市银帆合唱团","timestamp":"20170623104942000"},"EID":"8F28166A5064D2763C4FA4AF7F0A41EF","in_zone":"EFID1","SOS":0,"infocode":"10000","dis_EFID1":138.0,"steps":0,"loctype":2,"status":"1","info":"OK","timestamp":"20170623104942000"},"20170623130114000":{"result":{"country":"中国","province":"北京市","citycode":"010","adcode":"110108","city":"北京市","district":"海淀区","location":"116.305854763455,39.978215603299","type":"1","radius":"48","township":"海淀街道","desc":"北京市海淀区海淀街道苏州街乙29号海淀妇女儿童活动中心","timestamp":"20170623130114000"},"EID":"8F28166A5064D2763C4FA4AF7F0A41EF","gps_data":{"altitude":"182.900000","ground_speed":"13.038080","trace_degree":"343.170013"},"SOS":0,"infocode":"10000","dis_EFID1":1622.0,"steps":193,"loctype":2,"status":"1","info":"OK","timestamp":"20170623130114000"},"20170623130412000":{"result":{"country":"中国","city":"北京市","adcode":"110108","poi":"海淀图书馆","type":"3","province":"北京市","citycode":"010","road":"丹棱街","street":"海淀大街","location":"116.3103619,39.9789703","radius":"29","desc":"北京市 海淀区 丹棱街 靠近海淀图书馆","timestamp":"20170623130412000"},"EID":"8F28166A5064D2763C4FA4AF7F0A41EF","SOS":0,"infocode":"10000","dis_EFID1":1300.0,"steps":127,"loctype":2,"status":"1","info":"OK","timestamp":"20170623130412000"},"20170623211837000":{"result":{"country":"中国","city":"北京市","adcode":"110108","poi":"海淀区地方税务局知春里税务所","type":"3","province":"北京市","citycode":"010","road":"双榆树北路","street":"双榆树北路","location":"116.3240025,39.9735558","radius":"29","desc":"北京市 海淀区 双榆树北路 靠近海淀区地方税务局知春里税务所","timestamp":"20170623211837000"},"EID":"8F28166A5064D2763C4FA4AF7F0A41EF","in_zone":"EFID1","SOS":0,"infocode":"10000","dis_EFID1":10.0,"steps":0,"loctype":2,"status":"1","info":"OK","timestamp":"20170623211837000"},"20170623194623000":{"result":{"country":"中国","city":"北京市","adcode":"110108","poi":"渣打银行(中关村支行)","type":"3","province":"北京市","citycode":"010","road":"善缘街","street":"丹棱街","location":"116.3102802,39.9806757","radius":"25","desc":"北京市 海淀区 善缘街 靠近渣打银行(中关村支行)","timestamp":"20170623194623000"},"EID":"8F28166A5064D2763C4FA4AF7F0A41EF","SOS":0,"infocode":"10000","dis_EFID1":1403.0,"steps":75,"loctype":2,"status":"1","info":"OK","timestamp":"20170623194623000"},"20170623110452000":{"result":{"country":"中国","city":"北京市","adcode":"110108","poi":"苏州街(地铁站)","type":"3","province":"北京市","citycode":"010","road":"苏州街","street":"苏州街","location":"116.3060042,39.976062","radius":"35","desc":"北京市 海淀区 苏州街 靠近苏州街(地铁站)","timestamp":"20170623110452000"},"EID":"8F28166A5064D2763C4FA4AF7F0A41EF","SOS":0,"infocode":"10000","dis_EFID1":1550.0,"steps":4,"loctype":2,"status":"1","info":"OK","timestamp":"20170623110452000"},"20170623105255000":{"result":{"country":"中国","province":"北京市","citycode":"010","adcode":"110108","city":"北京市","district":"海淀区","location":"116.325058322483,39.976331380209","type":"1","radius":"27","township":"中关村街道","desc":"北京市海淀区中关村街道科学院南路大泥湾小区","timestamp":"20170623105255000"},"EID":"8F28166A5064D2763C4FA4AF7F0A41EF","EFence":{"Radius":200,"Desc":"北京市海淀区双榆树北路靠近海淀区地方税务局知春里税务所","Type":2,"Lng":116.323884,"EFID":"EFID1","Lat":39.973581,"Name":"家"},"gps_data":{"altitude":"69.900000","ground_speed":"15.353080","trace_degree":"299.359985"},"SOS":0,"dis_EFID1":322.0,"infocode":"10000","steps":75,"loctype":2,"status":"1","info":"OK","timestamp":"20170623105255000"},"20170623195645000":{"result":{"country":"中国","province":"北京市","citycode":"010","adcode":"110108","city":"北京市","district":"海淀区","location":"116.318574761285,39.972616373698","type":"1","radius":"62","township":"海淀街道","desc":"北京市海淀区海淀街道中国人民大学","timestamp":"20170623195645000"},"EID":"8F28166A5064D2763C4FA4AF7F0A41EF","gps_data":{"altitude":"250.100000","ground_speed":"9.185920","trace_degree":"164.289993"},"SOS":0,"infocode":"10000","dis_EFID1":465.0,"steps":139,"loctype":2,"status":"1","info":"OK","timestamp":"20170623195645000"},"20170623130832000":{"result":{"country":"中国","city":"北京市","adcode":"110108","poi":"理想国际会议中心","type":"3","province":"北京市","citycode":"010","road":"善缘街","street":"丹棱街","location":"116.310306,39.9797941","radius":"35","desc":"北京市 海淀区 善缘街 靠近理想国际会议中心","timestamp":"20170623130832000"},"EID":"8F28166A5064D2763C4FA4AF7F0A41EF","SOS":0,"infocode":"10000","dis_EFID1":1349.0,"steps":0,"loctype":2,"status":"1","info":"OK","timestamp":"20170623130832000"},"20170623000550000":{"result":{"country":"中国","province":"北京市","citycode":"010","adcode":"110108","city":"北京市","district":"海淀区","location":"116.312816840278,39.975632052952","type":"1","radius":"36","township":"海淀街道","desc":"北京市海淀区海淀街道海淀南路西4号东方凯德华快捷酒店","timestamp":"20170623000550000"},"EID":"8F28166A5064D2763C4FA4AF7F0A41EF","gps_data":{"altitude":"107.800000","ground_speed":"7.759880","trace_degree":"99.209999"},"SOS":0,"infocode":"10000","dis_EFID1":971.0,"steps":47,"loctype":2,"status":"1","info":"OK","timestamp":"20170623000550000"},"20170623000141000":{"result":{"country":"中国","province":"北京市","citycode":"010","adcode":"110108","city":"北京市","district":"海淀区","location":"116.308021647136,39.982998046875","type":"1","radius":"35","township":"海淀街道","desc":"北京市海淀区海淀街道海淀大街60号基督教堂","timestamp":"20170623000141000"},"EID":"8F28166A5064D2763C4FA4AF7F0A41EF","gps_data":{"altitude":"109.100000","ground_speed":"13.649240","trace_degree":"89.209999"},"SOS":0,"infocode":"10000","dis_EFID1":1711.0,"steps":0,"loctype":2,"status":"1","info":"OK","timestamp":"20170623000141000"},"20170623195112000":{"result":{"country":"中国","province":"北京市","citycode":"010","adcode":"110108","city":"北京市","district":"海淀区","location":"116.309298773872,39.980888400608","type":"1","radius":"55","township":"海淀街道","desc":"北京市海淀区海淀街道立方·庭","timestamp":"20170623195112000"},"EID":"8F28166A5064D2763C4FA4AF7F0A41EF","gps_data":{"altitude":"234.000000","ground_speed":"1.333440","trace_degree":"224.039993"},"SOS":0,"infocode":"10000","dis_EFID1":1486.0,"steps":135,"loctype":2,"status":"1","info":"OK","timestamp":"20170623195112000"},"20170623133811000":{"result":{"country":"中国","province":"北京市","citycode":"010","adcode":"110108","city":"北京市","district":"海淀区","location":"116.308033040365,39.979184027778","type":"1","radius":"62","township":"海淀街道","desc":"北京市海淀区海淀街道彩和坊路20号创富大厦","timestamp":"20170623133811000"},"EID":"8F28166A5064D2763C4FA4AF7F0A41EF","gps_data":{"altitude":"96.400000","ground_speed":"9.445200","trace_degree":"34.560001"},"SOS":0,"infocode":"10000","dis_EFID1":1489.0,"steps":0,"loctype":2,"status":"1","info":"OK","timestamp":"20170623133811000"},"20170623130713000":{"result":{"country":"中国","city":"北京市","adcode":"110108","poi":"理想国际会议中心","type":"3","province":"北京市","citycode":"010","road":"善缘街","street":"丹棱街","location":"116.310306,39.9797941","radius":"35","desc":"北京市 海淀区 善缘街 靠近理想国际会议中心","timestamp":"20170623130713000"},"EID":"8F28166A5064D2763C4FA4AF7F0A41EF","SOS":0,"infocode":"10000","dis_EFID1":1349.0,"steps":74,"loctype":2,"status":"1","info":"OK","timestamp":"20170623130713000"},"20170623133342000":{"result":{"country":"中国","province":"北京市","citycode":"010","adcode":"110108","city":"北京市","district":"海淀区","location":"116.306795247396,39.976985948351","type":"1","radius":"52","township":"海淀街道","desc":"北京市海淀区海淀街道种植培训中心长远天地大厦","timestamp":"20170623133342000"},"EID":"8F28166A5064D2763C4FA4AF7F0A41EF","gps_data":{"altitude":"164.000000","ground_speed":"0.407440","trace_degree":"264.440002"},"SOS":0,"infocode":"10000","dis_EFID1":1506.0,"steps":184,"loctype":2,"status":"1","info":"OK","timestamp":"20170623133342000"},"20170623001953000":{"result":{"country":"中国","city":"北京市","adcode":"110108","poi":"海淀区地方税务局知春里税务所","type":"3","province":"北京市","citycode":"010","road":"双榆树北路","street":"双榆树北路","location":"116.3239741,39.9735447","radius":"35","desc":"北京市 海淀区 双榆树北路 靠近海淀区地方税务局知春里税务所","timestamp":"20170623001953000"},"EID":"8F28166A5064D2763C4FA4AF7F0A41EF","in_zone":"EFID1","SOS":0,"infocode":"10000","dis_EFID1":8.0,"steps":10,"loctype":2,"status":"1","info":"OK","timestamp":"20170623001953000"},"20170623195535000":{"result":{"country":"中国","city":"北京市","adcode":"110108","poi":"中国人民大学附属中学","type":"3","province":"北京市","citycode":"010","road":"海淀南路","street":"海淀南路","location":"116.3132511,39.9757693","radius":"29","desc":"北京市 海淀区 海淀南路 靠近中国人民大学附属中学","timestamp":"20170623195535000"},"EID":"8F28166A5064D2763C4FA4AF7F0A41EF","SOS":0,"infocode":"10000","dis_EFID1":939.0,"steps":216,"loctype":2,"status":"1","info":"OK","timestamp":"20170623195535000"},"20170623110029000":{"result":{"country":"中国","province":"北京市","citycode":"010","adcode":"110108","city":"北京市","district":"海淀区","location":"116.304516059028,39.975750054254","type":"1","radius":"32","township":"海淀街道","desc":"北京市海淀区海淀街道海淀南路海淀南路31号院","timestamp":"20170623110029000"},"EID":"8F28166A5064D2763C4FA4AF7F0A41EF","gps_data":{"altitude":"70.800000","ground_speed":"0.351880","trace_degree":"113.209999"},"SOS":0,"infocode":"10000","dis_EFID1":1669.0,"steps":26,"loctype":2,"status":"1","info":"OK","timestamp":"20170623110029000"},"20170623105124000":{"result":{"country":"中国","province":"北京市","citycode":"010","adcode":"110108","city":"北京市","district":"海淀区","location":"116.325418836806,39.97344889323","type":"1","radius":"31","township":"中关村街道","desc":"北京市海淀区中关村街道科学院南路甲30号双榆树北路小区(双榆树北路)","timestamp":"20170623105124000"},"EID":"8F28166A5064D2763C4FA4AF7F0A41EF","in_zone":"EFID1","gps_data":{"altitude":"70.200000","ground_speed":"12.556560","trace_degree":"0.060000"},"SOS":0,"dis_EFID1":131.0,"infocode":"10000","steps":64,"loctype":2,"status":"1","info":"OK","timestamp":"20170623105124000"},"20170623000413000":{"result":{"country":"中国","province":"北京市","citycode":"010","adcode":"110108","city":"北京市","district":"海淀区","location":"116.311166992188,39.978148328994","type":"1","radius":"59","township":"海淀街道","desc":"北京市海淀区海淀街道海淀中街海兴大厦","timestamp":"20170623000413000"},"EID":"8F28166A5064D2763C4FA4AF7F0A41EF","gps_data":{"altitude":"108.300000","ground_speed":"10.982360","trace_degree":"161.009995"},"SOS":0,"infocode":"10000","dis_EFID1":1198.0,"steps":10,"loctype":2,"status":"1","info":"OK","timestamp":"20170623000413000"},"20170623001133000":{"result":{"country":"中国","city":"北京市","adcode":"110108","poi":"北里社区公共电子阅览室","type":"3","province":"北京市","citycode":"010","road":"双榆树北路","street":"双榆树北路","location":"116.3238732,39.9732777","radius":"25","desc":"北京市 海淀区 双榆树北路 靠近北里社区公共电子阅览室","timestamp":"20170623001133000"},"EID":"8F28166A5064D2763C4FA4AF7F0A41EF","in_zone":"EFID1","SOS":0,"infocode":"10000","dis_EFID1":33.0,"steps":47,"loctype":2,"status":"1","info":"OK","timestamp":"20170623001133000"},"20170623001303000":{"result":{"country":"中国","city":"北京市","adcode":"110108","poi":"北里社区公共电子阅览室","type":"3","province":"北京市","citycode":"010","road":"双榆树北路","street":"双榆树北路","location":"116.3238732,39.9732777","radius":"25","desc":"北京市 海淀区 双榆树北路 靠近北里社区公共电子阅览室","timestamp":"20170623001303000"},"EID":"8F28166A5064D2763C4FA4AF7F0A41EF","in_zone":"EFID1","SOS":0,"infocode":"10000","dis_EFID1":33.0,"steps":81,"loctype":2,"status":"1","info":"OK","timestamp":"20170623001303000"},"20170623134244000":{"result":{"country":"中国","city":"北京市","adcode":"110108","poi":"恒生银行(北京中关村支行)","type":"3","province":"北京市","citycode":"010","road":"善缘街","street":"丹棱街","location":"116.3102436,39.9805081","radius":"25","desc":"北京市 海淀区 善缘街 靠近恒生银行(北京中关村支行)","timestamp":"20170623134244000"},"EID":"8F28166A5064D2763C4FA4AF7F0A41EF","SOS":0,"infocode":"10000","dis_EFID1":1395.0,"steps":66,"loctype":2,"status":"1","info":"OK","timestamp":"20170623134244000"},"20170623110331000":{"result":{"country":"中国","city":"北京市","adcode":"110108","poi":"苏州街(地铁站)","type":"3","province":"北京市","citycode":"010","road":"苏州街","street":"苏州街","location":"116.3060042,39.976062","radius":"35","desc":"北京市 海淀区 苏州街 靠近苏州街(地铁站)","timestamp":"20170623110331000"},"EID":"8F28166A5064D2763C4FA4AF7F0A41EF","SOS":0,"infocode":"10000","dis_EFID1":1550.0,"steps":123,"loctype":2,"status":"1","info":"OK","timestamp":"20170623110331000"},"20170623132435000":{"result":{"country":"中国","province":"北京市","citycode":"010","adcode":"110108","city":"北京市","district":"海淀区","location":"116.306580674914,39.976781684028","type":"1","radius":"50","township":"海淀街道","desc":"北京市海淀区海淀街道银丰大厦","timestamp":"20170623132435000"},"EID":"8F28166A5064D2763C4FA4AF7F0A41EF","gps_data":{"altitude":"197.700000","ground_speed":"0.685240","trace_degree":"195.479996"},"SOS":0,"infocode":"10000","dis_EFID1":1518.0,"steps":201,"loctype":2,"status":"1","info":"OK","timestamp":"20170623132435000"},"20170623131654000":{"result":{"country":"中国","city":"北京市","adcode":"110108","poi":"苏州街(地铁站)","type":"3","province":"北京市","citycode":"010","road":"苏州街","street":"海淀南路","location":"116.3060178,39.976202","radius":"35","desc":"北京市 海淀区 苏州街 靠近苏州街(地铁站)","timestamp":"20170623131654000"},"EID":"8F28166A5064D2763C4FA4AF7F0A41EF","SOS":0,"infocode":"10000","dis_EFID1":1551.0,"steps":37,"loctype":2,"status":"1","info":"OK","timestamp":"20170623131654000"},"20170623133941000":{"result":{"country":"中国","province":"北京市","citycode":"010","adcode":"110108","city":"北京市","district":"海淀区","location":"116.309461805556,39.97998155382","type":"1","radius":"54","township":"海淀街道","desc":"北京市海淀区海淀街道善缘街1+1大厦(彩和坊路)","timestamp":"20170623133941000"},"EID":"8F28166A5064D2763C4FA4AF7F0A41EF","gps_data":{"altitude":"96.600000","ground_speed":"1.981640","trace_degree":"127.449997"},"SOS":0,"infocode":"10000","dis_EFID1":1421.0,"steps":65,"loctype":2,"status":"1","info":"OK","timestamp":"20170623133941000"},"20170623063724000":{"result":{"country":"中国","city":"北京市","adcode":"110108","poi":"海淀区地方税务局知春里税务所","type":"3","province":"北京市","citycode":"010","road":"双榆树北路","street":"双榆树北路","location":"116.3240129,39.9735691","radius":"29","desc":"北京市 海淀区 双榆树北路 靠近海淀区地方税务局知春里税务所","timestamp":"20170623063724000"},"EID":"8F28166A5064D2763C4FA4AF7F0A41EF","in_zone":"EFID1","SOS":0,"infocode":"10000","dis_EFID1":11.0,"steps":0,"loctype":2,"status":"1","info":"OK","timestamp":"20170623063724000"},"20170623195217000":{"result":{"country":"中国","city":"北京市","adcode":"110108","poi":"1+1大厦(彩和坊路)","type":"3","province":"北京市","citycode":"010","road":"海淀西街","street":"海淀西街","location":"116.3095947,39.9797274","radius":"55","desc":"北京市 海淀区 海淀西街 靠近1+1大厦(彩和坊路)","timestamp":"20170623195217000"},"EID":"8F28166A5064D2763C4FA4AF7F0A41EF","SOS":0,"infocode":"10000","dis_EFID1":1397.0,"steps":85,"loctype":2,"status":"1","info":"OK","timestamp":"20170623195217000"},"20170623105857000":{"result":{"country":"中国","province":"北京市","citycode":"010","adcode":"110108","city":"北京市","district":"海淀区","location":"116.307133789063,39.975851508247","type":"1","radius":"33","township":"海淀街道","desc":"北京市海淀区海淀街道倒座庙北路亿方大厦","timestamp":"20170623105857000"},"EID":"8F28166A5064D2763C4FA4AF7F0A41EF","gps_data":{"altitude":"71.000000","ground_speed":"11.537960","trace_degree":"262.079987"},"SOS":0,"infocode":"10000","dis_EFID1":1451.0,"steps":109,"loctype":2,"status":"1","info":"OK","timestamp":"20170623105857000"},"20170623200205000":{"result":{"country":"中国","city":"北京市","adcode":"110108","poi":"海淀区地方税务局知春里税务所","type":"3","province":"北京市","citycode":"010","road":"双榆树北路","street":"双榆树北路","location":"116.3240343,39.9735059","radius":"25","desc":"北京市 海淀区 双榆树北路 靠近海淀区地方税务局知春里税务所","timestamp":"20170623200205000"},"EID":"8F28166A5064D2763C4FA4AF7F0A41EF","in_zone":"EFID1","SOS":0,"infocode":"10000","dis_EFID1":15.0,"steps":35,"loctype":2,"status":"1","info":"OK","timestamp":"20170623200205000"},"20170623132624000":{"result":{"country":"中国","city":"北京市","adcode":"110108","poi":"中国光大银行(苏州街支行)","type":"3","province":"北京市","citycode":"010","road":"苏州街","street":"苏州街","location":"116.3065793,39.977516","radius":"35","desc":"北京市 海淀区 苏州街 靠近中国光大银行(苏州街支行)","timestamp":"20170623132624000"},"EID":"8F28166A5064D2763C4FA4AF7F0A41EF","SOS":0,"infocode":"10000","dis_EFID1":1539.0,"steps":134,"loctype":2,"status":"1","info":"OK","timestamp":"20170623132624000"},"20170623110146000":{"result":{"country":"中国","city":"北京市","adcode":"110108","poi":"中国民生银行(北京苏州街支行)","type":"3","province":"北京市","citycode":"010","road":"海淀南路","street":"海淀南路","location":"116.3046455,39.975634","radius":"29","desc":"北京市 海淀区 海淀南路 靠近中国民生银行(北京苏州街支行)","timestamp":"20170623110146000"},"EID":"8F28166A5064D2763C4FA4AF7F0A41EF","SOS":0,"infocode":"10000","dis_EFID1":1657.0,"steps":43,"loctype":2,"status":"1","info":"OK","timestamp":"20170623110146000"},"20170623195903000":{"result":{"country":"中国","city":"北京市","adcode":"110108","poi":"海淀区地方税务局知春里税务所","type":"3","province":"北京市","citycode":"010","road":"双榆树北路","street":"双榆树北路","location":"116.3238683,39.9735308","radius":"25","desc":"北京市 海淀区 双榆树北路 靠近海淀区地方税务局知春里税务所","timestamp":"20170623195903000"},"EID":"8F28166A5064D2763C4FA4AF7F0A41EF","in_zone":"EFID1","EFence":{"Radius":200,"Desc":"北京市海淀区双榆树北路靠近海淀区地方税务局知春里税务所","Type":1,"Lng":116.323884,"EFID":"EFID1","Lat":39.973581,"Name":"家"},"SOS":0,"dis_EFID1":5.0,"infocode":"10000","steps":115,"loctype":2,"status":"1","info":"OK","timestamp":"20170623195903000"},"20170623131535000":{"result":{"country":"中国","province":"北京市","citycode":"010","adcode":"110108","city":"北京市","district":"海淀区","location":"116.306512858073,39.976303439671","type":"1","radius":"64","township":"海淀街道","desc":"北京市海淀区海淀街道科发源毛发移植技术研究院亿方大厦","timestamp":"20170623131535000"},"EID":"8F28166A5064D2763C4FA4AF7F0A41EF","gps_data":{"altitude":"89.700000","ground_speed":"1.074160","trace_degree":"216.589996"},"SOS":0,"infocode":"10000","dis_EFID1":1512.0,"steps":45,"loctype":2,"status":"1","info":"OK","timestamp":"20170623131535000"},"20170623194913000":{"result":{"country":"中国","city":"北京市","adcode":"110108","poi":"理想国际会议中心","type":"3","province":"北京市","citycode":"010","road":"善缘街","street":"丹棱街","location":"116.3103266,39.9798739","radius":"38","desc":"北京市 海淀区 善缘街 靠近理想国际会议中心","timestamp":"20170623194913000"},"EID":"8F28166A5064D2763C4FA4AF7F0A41EF","SOS":0,"infocode":"10000","dis_EFID1":1352.0,"steps":110,"loctype":2,"status":"1","info":"OK","timestamp":"20170623194913000"},"20170623104654000":{"result":{"country":"中国","province":"北京市","citycode":"010","adcode":"110108","city":"北京市","district":"海淀区","location":"116.325398491754,39.973371853299","type":"1","radius":"29","township":"中关村街道","desc":"北京市海淀区中关村街道科学院南路甲30号双榆树北路小区(双榆树北路)","timestamp":"20170623104654000"},"EID":"8F28166A5064D2763C4FA4AF7F0A41EF","in_zone":"EFID1","gps_data":{"altitude":"69.300000","ground_speed":"5.259680","trace_degree":"355.140015"},"SOS":0,"dis_EFID1":131.0,"infocode":"10000","steps":213,"loctype":2,"status":"1","info":"OK","timestamp":"20170623104654000"},"20170623001021000":{"EID":"8F28166A5064D2763C4FA4AF7F0A41EF","EFence":{"Radius":200,"Desc":"北京市海淀区双榆树北路靠近海淀区地方税务局知春里税务所","Type":1,"Lng":116.323884,"EFID":"EFID1","Lat":39.973581,"Name":"家"},"gps_data":{"altitude":"46.600000","ground_speed":"7.519120","trace_degree":"10.330000"},"dis_EFID1":57.0,"steps":0,"loctype":2,"result":{"country":"中国","province":"北京市","citycode":"010","adcode":"110108","city":"北京市","district":"海淀区","location":"116.324053548178,39.973077256945","type":"1","radius":"46","township":"中关村街道","desc":"北京市海淀区中关村街道沃家百康健康管理中心(知春里店)知春里","timestamp":"20170623001021000"},"in_zone":"EFID1","SOS":0,"infocode":"10000","status":"1","info":"OK","timestamp":"20170623001021000"},"20170623133601000":{"result":{"country":"中国","city":"北京市","adcode":"110108","poi":"苏州街(地铁站)","type":"3","province":"北京市","citycode":"010","road":"苏州街","street":"苏州街","location":"116.3060276,39.9761789","radius":"35","desc":"北京市 海淀区 苏州街 靠近苏州街(地铁站)","timestamp":"20170623133601000"},"EID":"8F28166A5064D2763C4FA4AF7F0A41EF","SOS":0,"infocode":"10000","dis_EFID1":1550.0,"steps":150,"loctype":2,"status":"1","info":"OK","timestamp":"20170623133601000"},"20170623130542000":{"result":{"country":"中国","city":"北京市","adcode":"110108","poi":"海淀图书馆","type":"3","province":"北京市","citycode":"010","road":"丹棱街","street":"海淀大街","location":"116.3103575,39.9792258","radius":"29","desc":"北京市 海淀区 丹棱街 靠近海淀图书馆","timestamp":"20170623130542000"},"EID":"8F28166A5064D2763C4FA4AF7F0A41EF","SOS":0,"infocode":"10000","dis_EFID1":1313.0,"steps":14,"loctype":2,"status":"1","info":"OK","timestamp":"20170623130542000"},"20170623195809000":{"result":{"country":"中国","province":"北京市","citycode":"010","adcode":"110108","city":"北京市","district":"海淀区","location":"116.320089789497,39.972479926216","type":"1","radius":"65","township":"中关村街道","desc":"北京市海淀区中关村街道双榆树北里北京市中关村中学双榆树校区","timestamp":"20170623195809000"},"EID":"8F28166A5064D2763C4FA4AF7F0A41EF","gps_data":{"altitude":"18.700000","ground_speed":"23.687080","trace_degree":"98.050003"},"SOS":0,"infocode":"10000","dis_EFID1":346.0,"steps":95,"loctype":2,"status":"1","info":"OK","timestamp":"20170623195809000"},"20170623134405000":{"result":{"country":"中国","city":"北京市","adcode":"110108","poi":"恒生银行(北京中关村支行)","type":"3","province":"北京市","citycode":"010","road":"善缘街","street":"丹棱街","location":"116.3102715,39.980549","radius":"25","desc":"北京市 海淀区 善缘街 靠近恒生银行(北京中关村支行)","timestamp":"20170623134405000"},"EID":"8F28166A5064D2763C4FA4AF7F0A41EF","SOS":0,"infocode":"10000","dis_EFID1":1396.0,"steps":0,"loctype":2,"status":"1","info":"OK","timestamp":"20170623134405000"},"20170623000852000":{"result":{"country":"中国","province":"北京市","citycode":"010","adcode":"110108","city":"北京市","district":"海淀区","location":"116.31965874566,39.972584092882","type":"1","radius":"50","township":"中关村街道","desc":"北京市海淀区中关村街道双榆树北路知春里","timestamp":"20170623000852000"},"EID":"8F28166A5064D2763C4FA4AF7F0A41EF","gps_data":{"altitude":"49.600000","ground_speed":"10.778640","trace_degree":"89.080002"},"SOS":0,"infocode":"10000","dis_EFID1":377.0,"steps":53,"loctype":2,"status":"1","info":"OK","timestamp":"20170623000852000"},"20170623222001000":{"result":{"country":"中国","city":"北京市","adcode":"110108","poi":"海淀区地方税务局知春里税务所","type":"3","province":"北京市","citycode":"010","road":"双榆树北路","street":"双榆树北路","location":"116.3240679,39.9735628","radius":"25","desc":"北京市 海淀区 双榆树北路 靠近海淀区地方税务局知春里税务所","timestamp":"20170623222001000"},"EID":"8F28166A5064D2763C4FA4AF7F0A41EF","in_zone":"EFID1","SOS":0,"infocode":"10000","dis_EFID1":15.0,"steps":0,"loctype":2,"status":"1","info":"OK","timestamp":"20170623222001000"},"20170623105556000":{"result":{"country":"中国","province":"北京市","citycode":"010","adcode":"110108","city":"北京市","district":"海淀区","location":"116.316502549914,39.976093478733","type":"1","radius":"30","township":"海淀街道","desc":"北京市海淀区海淀街道海淀南路北京市海淀医院","timestamp":"20170623105556000"},"EID":"8F28166A5064D2763C4FA4AF7F0A41EF","gps_data":{"altitude":"70.200000","ground_speed":"18.983000","trace_degree":"263.269989"},"SOS":0,"infocode":"10000","dis_EFID1":689.0,"steps":42,"loctype":2,"status":"1","info":"OK","timestamp":"20170623105556000"},"20170623200034000":{"result":{"country":"中国","city":"北京市","adcode":"110108","poi":"海淀区地方税务局知春里税务所","type":"3","province":"北京市","citycode":"010","road":"双榆树北路","street":"双榆树北路","location":"116.3240126,39.973434","radius":"25","desc":"北京市 海淀区 双榆树北路 靠近海淀区地方税务局知春里税务所","timestamp":"20170623200034000"},"EID":"8F28166A5064D2763C4FA4AF7F0A41EF","in_zone":"EFID1","SOS":0,"infocode":"10000","dis_EFID1":19.0,"steps":110,"loctype":2,"status":"1","info":"OK","timestamp":"20170623200034000"},"20170623000721000":{"result":{"country":"中国","province":"北京市","citycode":"010","adcode":"110108","city":"北京市","district":"海淀区","location":"116.317001953125,39.977366536459","type":"1","radius":"38","township":"海淀街道","desc":"北京市海淀区海淀街道中关村大街北京市海淀医院","timestamp":"20170623000721000"},"EID":"8F28166A5064D2763C4FA4AF7F0A41EF","gps_data":{"altitude":"108.200000","ground_speed":"9.537800","trace_degree":"141.199997"},"SOS":0,"infocode":"10000","dis_EFID1":722.0,"steps":31,"loctype":2,"status":"1","info":"OK","timestamp":"20170623000721000"},"20170623105726000":{"result":{"country":"中国","province":"北京市","citycode":"010","adcode":"110108","city":"北京市","district":"海淀区","location":"116.311634657119,39.976037055122","type":"1","radius":"33","township":"海淀街道","desc":"北京市海淀区海淀街道海淀中街东方凯德华快捷酒店","timestamp":"20170623105726000"},"EID":"8F28166A5064D2763C4FA4AF7F0A41EF","gps_data":{"altitude":"70.400000","ground_speed":"7.222800","trace_degree":"257.540009"},"SOS":0,"infocode":"10000","dis_EFID1":1080.0,"steps":90,"loctype":2,"status":"1","info":"OK","timestamp":"20170623105726000"},"20170623195403000":{"result":{"country":"中国","city":"北京市","adcode":"110108","poi":"海淀图书馆","type":"3","province":"北京市","citycode":"010","road":"海淀中街","street":"海淀中街","location":"116.311033,39.978479","radius":"59","desc":"北京市 海淀区 海淀中街 靠近海淀图书馆","timestamp":"20170623195403000"},"EID":"8F28166A5064D2763C4FA4AF7F0A41EF","SOS":0,"infocode":"10000","dis_EFID1":1224.0,"steps":259,"loctype":2,"status":"1","info":"OK","timestamp":"20170623195403000"},"20170623132724000":{"result":{"country":"中国","city":"北京市","adcode":"110108","poi":"中国光大银行(苏州街支行)","type":"3","province":"北京市","citycode":"010","road":"苏州街","street":"苏州街","location":"116.3065793,39.977516","radius":"35","desc":"北京市 海淀区 苏州街 靠近中国光大银行(苏州街支行)","timestamp":"20170623132724000"},"EID":"8F28166A5064D2763C4FA4AF7F0A41EF","SOS":0,"infocode":"10000","dis_EFID1":1539.0,"steps":10,"loctype":2,"status":"1","info":"OK","timestamp":"20170623132724000"},"20170623131402000":{"result":{"country":"中国","province":"北京市","citycode":"010","adcode":"110108","city":"北京市","district":"海淀区","location":"116.305923936632,39.979060601129","type":"1","radius":"48","township":"海淀街道","desc":"北京市海淀区海淀街道苏州街白家大院","timestamp":"20170623131402000"},"EID":"8F28166A5064D2763C4FA4AF7F0A41EF","gps_data":{"altitude":"98.400000","ground_speed":"3.722520","trace_degree":"176.639999"},"SOS":0,"infocode":"10000","dis_EFID1":1649.0,"steps":138,"loctype":2,"status":"1","info":"OK","timestamp":"20170623131402000"}},"CID":50052}